{
    "success": true,
    "id": "BV1GY4y1L7bX",
    "service": "bilibili",
    "sourceUrl": "https://www.bilibili.com/video/BV1GY4y1L7bX",
    "htmlUrl": "https://bibigpt.co/video/BV1GY4y1L7bX",
    "costDuration": 714,
    "remainingTime": 16918,
    "detail": {
        "dbId": "604cd80e-ea42-4509-88ec-61deb556c5c7",
        "id": "BV1GY4y1L7bX",
        "author": "",
        "authorId": "",
        "embedId": "641899816",
        "pageId": "731233086",
        "url": "https://www.bilibili.com/video/BV1GY4y1L7bX",
        "type": "bilibili",
        "title": "横板视频 - 一口气看完李白一生，大唐有你才真的了不起",
        "chapters": [],
        "cover": "http://i0.hdslb.com/bfs/archive/1c83e1acc10f70f58debbef9fc66f5c92fbcd44b.jpg",
        "duration": 714,
        "subtitlesArray": [
            {
                "end": 5.4,
                "text": "他是千古留名的诗仙 也是出了名的酒鬼 还是师圣杜甫的偶像",
                "index": 0,
                "startTime": 0
            },
            {
                "end": 13.74,
                "text": "绣口艺图便是半个圣堂 他究竟有着怎样的人格魅力 本期视频让我们一口气看懂李白的传奇人生",
                "index": 1,
                "startTime": 5.4
            },
            {
                "end": 19.68,
                "text": "李白出生于长安元年 即公元701年 在公元762年离世",
                "index": 2,
                "startTime": 13.74
            },
            {
                "end": 27.72,
                "text": "享年61岁 一生中有40多年是在唐明皇的统治之下 见证了最光辉灿烂的圣堂时期",
                "index": 3,
                "startTime": 19.68
            },
            {
                "end": 32.82,
                "text": "关于李白的身世和家族 在当时就秽国独深 如今的一种说法是",
                "index": 4,
                "startTime": 27.72
            },
            {
                "end": 38.7,
                "text": "他父亲是西域的一位富商 也就是说李白是个富二代 另一种说法是",
                "index": 5,
                "startTime": 32.82
            },
            {
                "end": 45.9,
                "text": "他和唐朝皇室是同一个先祖 也是具有皇族血脉的人 而他究竟是富商之子还是皇族之后",
                "index": 6,
                "startTime": 38.7
            },
            {
                "end": 52.2,
                "text": "就是人者见人 智者见智的问题了 相传李白出生前 其母梦见太白行入怀",
                "index": 7,
                "startTime": 45.9
            },
            {
                "end": 58.92,
                "text": "于是父亲便为他取名为白 子太白 好清廉居士 因为在家中排行第十二",
                "index": 8,
                "startTime": 52.2
            },
            {
                "end": 66.72,
                "text": "又被称为李十二 在他很小的时候就接触过道教的书 所谓五岁通六甲就是这个意思",
                "index": 9,
                "startTime": 58.92
            },
            {
                "end": 81.12,
                "text": "民间传说他六岁时遇见一个老太婆 要把一根大蝶索磨成绣花针 受到感动的李白下决心用功读书",
                "index": 10,
                "startTime": 66.72
            },
            {
                "end": 90.72,
                "text": "得到了当时一些社会名流的夸赞与推崇 小小年纪的他还花费了很多时间学习剑术和道术 有着十五号剑术的字数",
                "index": 11,
                "startTime": 81.12
            },
            {
                "end": 97.8,
                "text": "据史料记载他剑术十分高超 是剑圣陪民的徒弟 十八岁时曾和一个叫东延子的尹氏",
                "index": 12,
                "startTime": 90.72
            },
            {
                "end": 105.42,
                "text": "隐居在民山修习道术 和许多文人志士一样 他也有着修身治国齐家平天下的人生理想",
                "index": 13,
                "startTime": 97.8
            },
            {
                "end": 116.88,
                "text": "但是却从未参加过科举考试入世 二十四岁时李白离开四川 踏上了远游的城途随后他这一生几乎都在路上再也没有回到过故乡",
                "index": 14,
                "startTime": 105.42
            },
            {
                "end": 127.56,
                "text": "游行足迹遍布湖北湖南安徽甘肃北京等地 一边游山玩水增长见识 一边拜业当地的名流希望能遇到自己的伯乐",
                "index": 15,
                "startTime": 116.88
            },
            {
                "end": 137.94,
                "text": "游行途中他创作出不少快适人口的明天 在金陵时写出了著名的长干行 其中那一句狼骑竹马来绕床弄青梅",
                "index": 16,
                "startTime": 127.56
            },
            {
                "end": 155.64,
                "text": "直接推升了青梅竹马这个成语 在扬州时为了结交好友不到一年的时间里就散金三十万 妥妥是灰尽如土的富二代结果就没钱了26岁时贫穷的他得了一场大病在贫病交加之时认识了当时的大诗人孟浩然",
                "index": 17,
                "startTime": 137.94
            },
            {
                "end": 169.62,
                "text": "孟浩然比李白大11岁他们之间有着深厚的友情 李白还曾经写下黄鹤楼送孟浩然之广龄 故人西辞黄鹤楼烟花三月下扬州孤帆远影碧宫尽",
                "index": 18,
                "startTime": 155.64
            },
            {
                "end": 210.06,
                "text": "惟见长江天际流 27岁时在孟浩然的作词下他迎许的第一任妻子唐高东时期的宰相徐宇诗的孙女成了豪门许家的贵婿二人成婚后有一儿一女度过了十年恩爱的时光入住许家的这十年是李白为数不多的安定时光在这几天他并不满足于贵婿的身份于是积极拜也名流希望得到引荐他先是拜也宰相张说不巧的是张说病重通过张说的儿子张记住到了钟南山玉真公主夜馆为逃公主欢心他积极显示却连公主的面都没见过 随后黯然离开长安",
                "index": 19,
                "startTime": 169.62
            },
            {
                "end": 235.8,
                "text": "后来他也曾给素有薄弱之称的韩朝宗写本求见内庇与韩经周书如今已是举世名片在当时却没能打动韩朝宗的心没等到回信的李白陷入了失望 后来妻子许氏因病去世李白伤心之余便开始放荡不羁的生活成天吟诗作画吟酒作乐 许氏去世一年后李白娶了一名刘氏女子为妻话说他这心变得还真快",
                "index": 20,
                "startTime": 210.06
            },
            {
                "end": 262.14,
                "text": "但是刘氏非常看不起贫穷落魄的李白时不时羞辱他面对刘氏的清灭 李白愤而离婚 后来他在山东仁城娶了第三任妻子有了心爱的小儿子可是好景不长五年后妻子因病离世经历了人生的诸多变迁后李白继续一路漂泊辗转在安徽江苏浙江等地不遗余力的照人举荐终于在42岁时得到了人生中的第一个机会",
                "index": 21,
                "startTime": 235.8
            },
            {
                "end": 338.88,
                "text": "好友丹秋生以道家流受招入朝得到了玉真公主的礼遇他便向公主引荐李白此时李白也在长安紫禁宫结识了贺知璋贺知璋读了蜀道南和乌七曲后惊讶于他规礼的诗歌和非凡的文采给他写了个外号叫折仙人之后在玉真公主和贺知璋的赞赏推荐下玄宗十分钦慕李白的师父不久后便招他进宫 缩头大半生的李白终于得到了赏识成为盛唐以来最被君王宠幸的诗人唐玄宗不仅亲自为他调羹更封他为供奉汉林曹拟文告陪侍左右一时间春光无限此前的李白正跃跃欲试准备在政治上一展铜图却没想到玄宗只是让他写诗文娱乐天天陪他玩李白很郁闷他多年苦学四处求索是为了成为一个救世济民的大贤臣而不是一个随侍皇帝的小跟班于是逐渐对自己的工作也越来越不上心整天喝的酩酊大醉就连玄宗 花园赏花人美花娇玄宗心情大好于是让人宣李白来作诗",
                "index": 22,
                "startTime": 262.14
            },
            {
                "end": 351.3,
                "text": "没想到朱子又喝醉了唐玄宗没生气顺势让他对着写诗 而喝得醉醺醺的李白竟然要专门服侍皇上的高丽士给他脱靴 杨贵妃亲自研墨才同意写诗",
                "index": 23,
                "startTime": 338.88
            },
            {
                "end": 379.44,
                "text": "这一说丽士脱靴贵妃研墨让李白出尽了风头 随后他瞧见美艳娇媚的杨贵妃稍作思索便提笔成诗写出了一组三首著名的清平调 尤其是第一首的第一句云想一场花想中春风福建路华农堪称神来之笔令所有读者为之赞叹也令杨贵妃喜笑颜开玄宗对他宠爱有加给他无上的荣华与尊崇",
                "index": 24,
                "startTime": 351.3
            },
            {
                "end": 398.76,
                "text": "但他不愿成为被王公圈养的宠物产生了退隐江湖潜心修道的念头 那一年李白在京城相继送走了智友贺志章和袁丹秋好友的离开使他感到前所未有的孤单 不久后就向玄宗提出辞职因为狂放不羁和直言不讳他得罪过不少人",
                "index": 25,
                "startTime": 379.44
            },
            {
                "end": 421.92,
                "text": "仅此时也没人挽留最后李白带着玄宗给的一大笔离职金失望的离开了京城公元744年心灰意冷的李白来到了洛阳遇到了科考失败的杜甫 这时李白43岁已是名动天下的大诗人而32岁的杜甫当时还岌岌无名 李白看着初出茅庐的杜甫犹如看到了十年前的自己",
                "index": 26,
                "startTime": 398.76
            },
            {
                "end": 432.54,
                "text": "此时的李白经历过仕途成功的幻梦 已经意识到人生苦短应当及时醒乐 而杜甫看着近在眼前的偶像没有一味的自卑拘束",
                "index": 27,
                "startTime": 421.92
            },
            {
                "end": 453.72,
                "text": "聊天中李白对杜甫的诗作非常欣赏两人一见如故成了朋友那些日子里他们白天相携游玩晚上纵行饮酒相谈试欢之后两人还见过两次面 下期关于杜甫一生的视频里会详细提到杜甫对李白的感情非常深厚 而李白对杜甫的感情却是淡淡的",
                "index": 28,
                "startTime": 432.54
            },
            {
                "end": 485.94,
                "text": "他曾经为王昌龄孟浩然汪伦慷慨赠诗却只给为他写了15首诗的杜甫回了三首 或许偶像与粉丝之间的友情本就是不对等的 其实李白是有些社交牛逼症在身上的到哪儿都能交到朋友朋友多爱好也多不挂念杜甫也是情理之中747年46岁的李白邂逅了最后一位妻子武则天时期的宰相宗楚克的孙女宗玉她又一次成功入费豪门两人还流传着千金买币的佳话",
                "index": 29,
                "startTime": 453.72
            },
            {
                "end": 569.7,
                "text": "一次好演后李白酒醉良缘一时兴起挥笔在墙上写下良缘银宗室知道后赶来欣赏还花了千金将此墙壁买下由此诞生了千金买币的典故宗室与李白一样爱好修道两人婚后十分恩爱 当时的大唐已经是暗流涌动看似繁华的帝国已是危机四伏755年安禄山叛乱后天下大乱李白和妻子一起逃难避武庐山白天读书夜晚修道山外生灵涂炭山内一片安然在勇王多次下宾处邀请下李白决定出山 然而他万万没想到勇王不是平定叛乱的忠臣义士而是从事叛乱的逆臣贼子不久后勇王兵败被杀李白也被捕入狱造化弄人关押他的恰恰是曾经的好友边塞诗人高士本以为危难时刻朋友能伸出援手但是离夫人及私不复拜榜高士都避而不见随后在御史忠诚宋若司的激励相助下李白逃过一死但还是因为参与谋反作乱被流放夜郎759年朝廷因关中遭遇大旱宣布大赦天下李白在流放途中重获自由随即写下那首",
                "index": 30,
                "startTime": 485.94
            },
            {
                "end": 640.92,
                "text": "一日还两岸原声提不住荆州已过万重山轻松愉快的心情跃然直煞随后的两年时间里他往来在宣场金陵两地之间生活潦倒窘迫以投奔朋友为生可谓是顽井凄凉看透事态炎凉后的李白写下了旷世奇作独坐静亭山 重摇高飞尽孤云独去弦相看两不厌只有静亭山表达了生命最后历程中旷世的孤独感即将离世的李白绝对不会想到自己的潇洒不羁会令千年后的世人也心直神乱那些最久后随意写下的诗篇会成为学生教材中的范例久久流传而他会被后人誉为诗仙在中国文坛上有着举足轻重的地位762年李白语士长辞结束了他传奇而坎坷的一生关于死因历来众说纷纭总体非概括为三种一是对死二是病死三是溺死第一种鉴于旧唐 说李白以饮酒过度对死于宣场",
                "index": 31,
                "startTime": 569.7
            },
            {
                "end": 652.74,
                "text": "第二种鉴于其他正式或专家学者的考证之说 61岁的李白为挽救国家威望主动请缨沙迪因病中途返回 第二年病死在当土县",
                "index": 32,
                "startTime": 640.92
            },
            {
                "end": 667.26,
                "text": "而第三种则多鉴于民间传说说李白在当途的江上饮酒醉酒后看到水中的月亮很美 于是水中捞月而溺死暴月而终极服浪漫色彩 他这一生放荡不羁爱自由",
                "index": 33,
                "startTime": 652.74
            },
            {
                "end": 684.66,
                "text": "后知章称他为折仙人 杜甫评价他笔落经风雨诗成记鬼神 李白不仅是当代文学的巨星也是中国文学史上举足轻重的人物有过春风得意的高光时刻也有过彷徨诗意的低落时光",
                "index": 34,
                "startTime": 667.26
            },
            {
                "end": 693,
                "text": "更多的时候是与知己好友把酒言欢 写过的神仙绝句不计其数 留给世人绚丽的文学瑰宝",
                "index": 35,
                "startTime": 684.66
            },
            {
                "end": 700.02,
                "text": "亦是不少后人心目中的偶像 余光中曾经写道酒入喉肠 积分酿成的月光",
                "index": 36,
                "startTime": 693
            },
            {
                "end": 707.82,
                "text": "余下的三分笑成溅气 袖口一吐就是半个盛唐 一千个人心中就有一千个李白",
                "index": 37,
                "startTime": 700.02
            },
            {
                "end": 719.76,
                "text": "你觉得李白是怎样的人呢 提起李白 你最先想到的是哪句诗呢",
                "index": 38,
                "startTime": 707.82
            }
        ],
        "rawLang": "",
        "descriptionText": "一口气看完李白一生，大唐有你才真的了不起 一口气看完李白一生，大唐有你才真的了不起",
        "contentText": ""
    }
}